[
  {
    "file": "multiple_choice/assessments/javascript/easy/assessment10.js",
    "total": 30,
    "counts": {
      "A": 6,
      "B": 7,
      "C": 6,
      "D": 11
    },
    "skew": 0.36666666666666664,
    "questionNotes": [
      {
        "index": 0,
        "notes": []
      },
      {
        "index": 1,
        "notes": []
      },
      {
        "index": 2,
        "notes": []
      },
      {
        "index": 3,
        "notes": []
      },
      {
        "index": 4,
        "notes": []
      },
      {
        "index": 5,
        "notes": []
      },
      {
        "index": 6,
        "notes": []
      },
      {
        "index": 7,
        "notes": []
      },
      {
        "index": 8,
        "notes": []
      },
      {
        "index": 9,
        "notes": []
      },
      {
        "index": 10,
        "notes": []
      },
      {
        "index": 11,
        "notes": []
      },
      {
        "index": 12,
        "notes": []
      },
      {
        "index": 13,
        "notes": []
      },
      {
        "index": 14,
        "notes": []
      },
      {
        "index": 15,
        "notes": []
      },
      {
        "index": 16,
        "notes": []
      },
      {
        "index": 17,
        "notes": []
      },
      {
        "index": 18,
        "notes": []
      },
      {
        "index": 19,
        "notes": []
      },
      {
        "index": 20,
        "notes": []
      },
      {
        "index": 21,
        "notes": []
      },
      {
        "index": 22,
        "notes": []
      },
      {
        "index": 23,
        "notes": []
      },
      {
        "index": 24,
        "notes": []
      },
      {
        "index": 25,
        "notes": []
      },
      {
        "index": 26,
        "notes": []
      },
      {
        "index": 27,
        "notes": []
      },
      {
        "index": 28,
        "notes": []
      },
      {
        "index": 29,
        "notes": []
      }
    ]
  }
]